izen/__init__.py
izen/amq.py
izen/chaos.py
izen/crawler.py
izen/dec.py
izen/helper.py
izen/icfg.py
izen/prettify.py
izen/rds.py
izen/schedule.py
izen/slnm.py
izen-0.2.3.dist-info/LICENSE
izen-0.2.3.dist-info/METADATA
izen-0.2.3.dist-info/WHEEL
izen-0.2.3.dist-info/top_level.txt
izen-0.2.3.dist-info/RECORD
