Metadata-Version: 2.1
Name: izen
Version: 0.2.3
Summary: encapsulation of some useful features
Home-page: https://github.com/coghost/izen
Author: lihe
Author-email: imanux@sina.com
License: GPL
Keywords: izen,tool
Platform: UNKNOWN
Requires-Dist: bs4
Requires-Dist: click
Requires-Dist: clint
Requires-Dist: hot-redis
Requires-Dist: logzero
Requires-Dist: numpy
Requires-Dist: paho-mqtt
Requires-Dist: profig
Requires-Dist: psutil
Requires-Dist: pycryptodome
Requires-Dist: requests
Requires-Dist: selenium
Requires-Dist: tqdm
Requires-Dist: wcwidth
